{
  "schema": "yggdrasil.bench.v1",
  "created_at": 1779646687093,
  "repo": "YdlTavern",
  "node_version": "v24.15.0",
  "git": {
    "commit": "b13a302d313818bc0a7303672e4731fe7bb4894f",
    "branch": "main",
    "dirty": true
  },
  "env": {
    "os": "linux",
    "arch": "x64",
    "num_cpus": 14
  },
  "packages": {
    "@ydltavern/engine-core": {
      "schema": "yggdrasil.bench.v1",
      "created_at": 1779646635872,
      "package": "@ydltavern/engine-core",
      "node_version": "v24.15.0",
      "git": {
        "commit": "b13a302d313818bc0a7303672e4731fe7bb4894f",
        "branch": "main",
        "dirty": true
      },
      "env": {
        "os": "linux",
        "arch": "x64",
        "num_cpus": 14
      },
      "benchmarks": [
        {
          "name": "prompt_manager.compile.small",
          "iterations": 506939,
          "samples": 506939,
          "min_ms": 0.0015530000000580912,
          "p50_ms": 0.0016829999999572465,
          "p95_ms": 0.00277399999959016,
          "p99_ms": 0.003576000000066415,
          "max_ms": 0.5016930000001594,
          "mean_ms": 0.0019726286732730585,
          "rsd_pct": 0.540403983961035,
          "throughput": {
            "value": 549756,
            "unit": "ops/s"
          }
        },
        {
          "name": "prompt_manager.compile.medium",
          "iterations": 34983,
          "samples": 34983,
          "min_ms": 0.021252999999887834,
          "p50_ms": 0.02409799999986717,
          "p95_ms": 0.04108399999950052,
          "p99_ms": 0.05225837999994839,
          "max_ms": 1.2945300000001225,
          "mean_ms": 0.028585819226478633,
          "rsd_pct": 0.6234048210986662,
          "throughput": {
            "value": 37580,
            "unit": "ops/s"
          }
        },
        {
          "name": "prompt_manager.compile.large",
          "iterations": 4649,
          "samples": 4649,
          "min_ms": 0.19088800000008632,
          "p50_ms": 0.20463900000049762,
          "p95_ms": 0.2523830000000089,
          "p99_ms": 0.6207530000002572,
          "max_ms": 1.5395020000005388,
          "mean_ms": 0.2151248597547839,
          "rsd_pct": 0.8303312119169938,
          "throughput": {
            "value": 4780,
            "unit": "ops/s"
          }
        },
        {
          "name": "world_info.evaluate.small",
          "iterations": 18590,
          "samples": 18590,
          "min_ms": 0.04765399999996589,
          "p50_ms": 0.05045900000004622,
          "p95_ms": 0.0649409999996351,
          "p99_ms": 0.09126531000017174,
          "max_ms": 1.8654499999993277,
          "mean_ms": 0.053795471436261635,
          "rsd_pct": 0.6090411438816994,
          "throughput": {
            "value": 19088,
            "unit": "ops/s"
          }
        },
        {
          "name": "world_info.evaluate.medium",
          "iterations": 1651,
          "samples": 1651,
          "min_ms": 0.5532320000002073,
          "p50_ms": 0.586314999998649,
          "p95_ms": 0.6957359999996697,
          "p99_ms": 1.0745259999994232,
          "max_ms": 1.2787440000010974,
          "mean_ms": 0.6057628231374758,
          "rsd_pct": 0.5866073699641329,
          "throughput": {
            "value": 1667,
            "unit": "ops/s"
          }
        },
        {
          "name": "world_info.evaluate.large",
          "iterations": 106,
          "samples": 106,
          "min_ms": 8.35583299999962,
          "p50_ms": 9.192944000000352,
          "p95_ms": 11.673878000001423,
          "p99_ms": 12.4066248000001,
          "max_ms": 13.567302000001291,
          "mean_ms": 9.504205556603749,
          "rsd_pct": 2.0035490685080806,
          "throughput": {
            "value": 106,
            "unit": "ops/s"
          }
        },
        {
          "name": "macros.expand.short",
          "iterations": 33883,
          "samples": 33883,
          "min_ms": 0.024507999998604646,
          "p50_ms": 0.026862000000619446,
          "p95_ms": 0.042347000000518165,
          "p99_ms": 0.05410417999897618,
          "max_ms": 2.005008000000089,
          "mean_ms": 0.02951349113124559,
          "rsd_pct": 0.7331140321167665,
          "throughput": {
            "value": 35592,
            "unit": "ops/s"
          }
        },
        {
          "name": "macros.expand.long",
          "iterations": 50,
          "samples": 50,
          "min_ms": 28.27249699999993,
          "p50_ms": 33.43062699999973,
          "p95_ms": 35.63368799999989,
          "p99_ms": 70.08556984000049,
          "max_ms": 102.81280900000093,
          "mean_ms": 34.43587786000001,
          "rsd_pct": 8.306650904586025,
          "throughput": {
            "value": 30,
            "unit": "ops/s"
          }
        },
        {
          "name": "tokenizer.gpt.encode.short",
          "iterations": 283937,
          "samples": 283937,
          "min_ms": 0.0022339999995892867,
          "p50_ms": 0.002484000000549713,
          "p95_ms": 0.0038860000004206086,
          "p99_ms": 0.004968000001099426,
          "max_ms": 211.98488499999985,
          "mean_ms": 0.003521914149967809,
          "rsd_pct": 41.55893269692278,
          "throughput": {
            "value": 388390,
            "unit": "ops/s"
          }
        },
        {
          "name": "tokenizer.gpt.encode.long",
          "iterations": 3852,
          "samples": 3852,
          "min_ms": 0.23272299999916868,
          "p50_ms": 0.25027550000049814,
          "p95_ms": 0.28103900000132853,
          "p99_ms": 0.6123815000000999,
          "max_ms": 9.635839999999007,
          "mean_ms": 0.2596293904465031,
          "rsd_pct": 1.9193200313258152,
          "throughput": {
            "value": 3941,
            "unit": "ops/s"
          }
        },
        {
          "name": "tokenizer.llama3.encode.short",
          "iterations": 28152,
          "samples": 28152,
          "min_ms": 0.025969000000259257,
          "p50_ms": 0.032189999999900465,
          "p95_ms": 0.0527620000011666,
          "p99_ms": 0.074351389999465,
          "max_ms": 1.7836910000005446,
          "mean_ms": 0.035522584363454734,
          "rsd_pct": 0.7876730101051866,
          "throughput": {
            "value": 29961,
            "unit": "ops/s"
          }
        },
        {
          "name": "tokenizer.llama3.encode.long",
          "iterations": 177,
          "samples": 177,
          "min_ms": 3.7406950000004144,
          "p50_ms": 4.606205000000045,
          "p95_ms": 13.233679999997548,
          "p99_ms": 19.336716919999457,
          "max_ms": 20.809478000002855,
          "mean_ms": 5.68111435028258,
          "rsd_pct": 7.87489048473878,
          "throughput": {
            "value": 200,
            "unit": "ops/s"
          }
        }
      ]
    },
    "@ydltavern/importers": {
      "schema": "yggdrasil.bench.v1",
      "created_at": 1779646643991,
      "package": "@ydltavern/importers",
      "node_version": "v24.15.0",
      "git": {
        "commit": "b13a302d313818bc0a7303672e4731fe7bb4894f",
        "branch": "main",
        "dirty": true
      },
      "env": {
        "os": "linux",
        "arch": "x64",
        "num_cpus": 14
      },
      "benchmarks": [
        {
          "name": "import.character.png.small",
          "iterations": 66393,
          "samples": 66393,
          "min_ms": 0.010947000000214757,
          "p50_ms": 0.012308999999731896,
          "p95_ms": 0.020293000000037864,
          "p99_ms": 0.03147979999977908,
          "max_ms": 3.638305000000173,
          "mean_ms": 0.015061892081996991,
          "rsd_pct": 1.0898378823578758,
          "throughput": {
            "value": 71977,
            "unit": "ops/s"
          }
        },
        {
          "name": "import.character.png.large",
          "iterations": 61761,
          "samples": 61761,
          "min_ms": 0.010787000000163971,
          "p50_ms": 0.017067000000224652,
          "p95_ms": 0.021423000000140746,
          "p99_ms": 0.031893599999966694,
          "max_ms": 4.780115000000023,
          "mean_ms": 0.01619158721523345,
          "rsd_pct": 1.4167191922875837,
          "throughput": {
            "value": 67588,
            "unit": "ops/s"
          }
        },
        {
          "name": "import.world_book.small",
          "iterations": 59899,
          "samples": 59899,
          "min_ms": 0.014181999999891559,
          "p50_ms": 0.014913999999407679,
          "p95_ms": 0.02548099999967235,
          "p99_ms": 0.03300119999979867,
          "max_ms": 1.4196139999999104,
          "mean_ms": 0.016694963054474297,
          "rsd_pct": 0.4769961338358982,
          "throughput": {
            "value": 62744,
            "unit": "ops/s"
          }
        },
        {
          "name": "import.world_book.large",
          "iterations": 564,
          "samples": 564,
          "min_ms": 1.5126280000004044,
          "p50_ms": 1.6308940000003531,
          "p95_ms": 2.6578349999999773,
          "p99_ms": 2.810961500000021,
          "max_ms": 3.465404999999919,
          "mean_ms": 1.7751433971631456,
          "rsd_pct": 1.6318043588422408,
          "throughput": {
            "value": 580,
            "unit": "ops/s"
          }
        },
        {
          "name": "import.jsonl.small",
          "iterations": 6425,
          "samples": 6425,
          "min_ms": 0.13228600000002189,
          "p50_ms": 0.14737999999942986,
          "p95_ms": 0.19663700000000972,
          "p99_ms": 0.24951675999960582,
          "max_ms": 1.4350279999998747,
          "mean_ms": 0.1556531833463168,
          "rsd_pct": 0.6057462970889379,
          "throughput": {
            "value": 6569,
            "unit": "ops/s"
          }
        },
        {
          "name": "import.jsonl.large",
          "iterations": 63,
          "samples": 63,
          "min_ms": 14.501568000000589,
          "p50_ms": 15.406488999999965,
          "p95_ms": 18.460533000000396,
          "p99_ms": 18.867316900000098,
          "max_ms": 19.088412000000062,
          "mean_ms": 15.89330377777779,
          "rsd_pct": 1.9298808841632629,
          "throughput": {
            "value": 63,
            "unit": "ops/s"
          }
        }
      ]
    },
    "@ydltavern/st-compat": {
      "schema": "yggdrasil.bench.v1",
      "created_at": 1779646672209,
      "package": "@ydltavern/st-compat",
      "node_version": "v24.15.0",
      "git": {
        "commit": "b13a302d313818bc0a7303672e4731fe7bb4894f",
        "branch": "main",
        "dirty": true
      },
      "env": {
        "os": "linux",
        "arch": "x64",
        "num_cpus": 14
      },
      "benchmarks": [
        {
          "name": "chat.proxy.read",
          "iterations": 4,
          "samples": 4,
          "min_ms": 1.1606010000004972,
          "p50_ms": 1.2216300000004594,
          "p95_ms": 1.6605997699999262,
          "p99_ms": 1.6605997699999262,
          "max_ms": 2.1254149999999754,
          "mean_ms": 1.2483552244389033,
          "rsd_pct": 0.555677383688395,
          "throughput": {
            "value": 805,
            "unit": "ops/s"
          }
        },
        {
          "name": "chat.proxy.write",
          "iterations": 4,
          "samples": 4,
          "min_ms": 4.601357999999891,
          "p50_ms": 5.207722999999987,
          "p95_ms": 7.341099299999649,
          "p99_ms": 7.341099299999649,
          "max_ms": 8.2948379999998,
          "mean_ms": 5.445719635869527,
          "rsd_pct": 1.677786408989075,
          "throughput": {
            "value": 186,
            "unit": "ops/s"
          }
        },
        {
          "name": "chat.proxy.iterate",
          "iterations": 4,
          "samples": 4,
          "min_ms": 0.9532770000005257,
          "p50_ms": 1.0086729999993622,
          "p95_ms": 1.5812717199996218,
          "p99_ms": 1.5812717199996218,
          "max_ms": 2.036124999999629,
          "mean_ms": 1.043744089676732,
          "rsd_pct": 0.7328321207901717,
          "throughput": {
            "value": 967,
            "unit": "ops/s"
          }
        },
        {
          "name": "eventSource.emit.no_listeners",
          "iterations": 4,
          "samples": 4,
          "min_ms": 0.000039999998989515007,
          "p50_ms": 0.00004000000080850441,
          "p95_ms": 0.00005100000089441892,
          "p99_ms": 0.00005100000089441892,
          "max_ms": 0.5498879999995552,
          "mean_ms": 0.00004375585202746824,
          "rsd_pct": 0.23059423255880895,
          "throughput": {
            "value": 23744718,
            "unit": "ops/s"
          }
        },
        {
          "name": "eventSource.emit.10_listeners",
          "iterations": 4,
          "samples": 4,
          "min_ms": 0.00007999999797903001,
          "p50_ms": 0.00010000000111176632,
          "p95_ms": 0.00015999999959603883,
          "p99_ms": 0.00015999999959603883,
          "max_ms": 48.59639600000082,
          "mean_ms": 0.0001150991076940967,
          "rsd_pct": 13.019128445645459,
          "throughput": {
            "value": 10045569,
            "unit": "ops/s"
          }
        },
        {
          "name": "eventSource.emit.100_listeners",
          "iterations": 4,
          "samples": 4,
          "min_ms": 0.00042100000064237975,
          "p50_ms": 0.0005410000012489036,
          "p95_ms": 0.0009620000018912833,
          "p99_ms": 0.0009620000018912833,
          "max_ms": 3.618042999998579,
          "mean_ms": 0.0006136549333870113,
          "rsd_pct": 0.835149857586605,
          "throughput": {
            "value": 1735791,
            "unit": "ops/s"
          }
        },
        {
          "name": "slash.parse.simple",
          "iterations": 4,
          "samples": 4,
          "min_ms": 0.0005710000004910398,
          "p50_ms": 0.0006410000023606699,
          "p95_ms": 0.0018020000024989713,
          "p99_ms": 0.0018020000024989713,
          "max_ms": 20.357662000002165,
          "mean_ms": 0.0007773913751576853,
          "rsd_pct": 4.663841089176857,
          "throughput": {
            "value": 1460694,
            "unit": "ops/s"
          }
        },
        {
          "name": "slash.parse.pipe",
          "iterations": 4,
          "samples": 4,
          "min_ms": 0.00046099999963189475,
          "p50_ms": 0.0005410000012489036,
          "p95_ms": 0.0015020000028016511,
          "p99_ms": 0.0015020000028016511,
          "max_ms": 1.3706180000008317,
          "mean_ms": 0.000623728042747376,
          "rsd_pct": 0.6422853325481932,
          "throughput": {
            "value": 1743108,
            "unit": "ops/s"
          }
        },
        {
          "name": "slash.execute.simple",
          "iterations": 4,
          "samples": 4,
          "min_ms": 0.0006009999997331761,
          "p50_ms": 0.0006700000012642704,
          "p95_ms": 0.0017520000001240987,
          "p99_ms": 0.0017520000001240987,
          "max_ms": 1.1892640000005485,
          "mean_ms": 0.0007570688432907398,
          "rsd_pct": 0.5014504307648364,
          "throughput": {
            "value": 1416583,
            "unit": "ops/s"
          }
        }
      ]
    },
    "@ydltavern/extensions": {
      "schema": "yggdrasil.bench.v1",
      "created_at": 1779646679294,
      "package": "@ydltavern/extensions",
      "node_version": "v24.15.0",
      "git": {
        "commit": "b13a302d313818bc0a7303672e4731fe7bb4894f",
        "branch": "main",
        "dirty": true
      },
      "env": {
        "os": "linux",
        "arch": "x64",
        "num_cpus": 14
      },
      "benchmarks": [
        {
          "name": "sandbox.bootstrap",
          "iterations": 4,
          "samples": 4,
          "min_ms": 0.1308339999995951,
          "p50_ms": 0.14313399999991816,
          "p95_ms": 0.26907519999999774,
          "p99_ms": 0.26907519999999774,
          "max_ms": 4.285963999999694,
          "mean_ms": 0.16023998910431142,
          "rsd_pct": 1.3652972381726498,
          "throughput": {
            "value": 6542,
            "unit": "ops/s"
          }
        },
        {
          "name": "sandbox.invoke.simple",
          "iterations": 4,
          "samples": 4,
          "min_ms": 0.0024939999998423446,
          "p50_ms": 0.0027540000000954024,
          "p95_ms": 0.004395999999815103,
          "p99_ms": 0.004395999999815103,
          "max_ms": 2.6516349999997146,
          "mean_ms": 0.0029266016523555594,
          "rsd_pct": 0.6307534152998096,
          "throughput": {
            "value": 355996,
            "unit": "ops/s"
          }
        },
        {
          "name": "regex.apply.short",
          "iterations": 4,
          "samples": 4,
          "min_ms": 0.003454000000601809,
          "p50_ms": 0.004017000000203552,
          "p95_ms": 0.013881559999535964,
          "p99_ms": 0.013881559999535964,
          "max_ms": 16.040948999999728,
          "mean_ms": 0.005095690381919489,
          "rsd_pct": 3.4528452973274053,
          "throughput": {
            "value": 226881,
            "unit": "ops/s"
          }
        },
        {
          "name": "regex.apply.long",
          "iterations": 4,
          "samples": 4,
          "min_ms": 1.2574119999999311,
          "p50_ms": 1.3583189999999377,
          "p95_ms": 1.9341977599999167,
          "p99_ms": 1.9341977599999167,
          "max_ms": 2.962601000000177,
          "mean_ms": 1.4193074070921823,
          "rsd_pct": 0.8648021373777394,
          "throughput": {
            "value": 712,
            "unit": "ops/s"
          }
        },
        {
          "name": "loader.parse_manifest",
          "iterations": 4,
          "samples": 4,
          "min_ms": 0.0037449999999807915,
          "p50_ms": 0.003945999999814376,
          "p95_ms": 0.010846999999648688,
          "p99_ms": 0.010846999999648688,
          "max_ms": 1.0683960000005754,
          "mean_ms": 0.004340458251407811,
          "rsd_pct": 0.5447907080968966,
          "throughput": {
            "value": 243512,
            "unit": "ops/s"
          }
        }
      ]
    },
    "@ydltavern/surface": {
      "schema": "yggdrasil.bench.v1",
      "created_at": 1779646686946,
      "package": "@ydltavern/surface",
      "node_version": "v24.15.0",
      "git": {
        "commit": "b13a302d313818bc0a7303672e4731fe7bb4894f",
        "branch": "main",
        "dirty": true
      },
      "env": {
        "os": "linux",
        "arch": "x64",
        "num_cpus": 14
      },
      "benchmarks": [
        {
          "name": "formatting.markdown.short",
          "iterations": 4,
          "samples": 4,
          "min_ms": 0.23840199999995093,
          "p50_ms": 0.38269200000002,
          "p95_ms": 0.699504049999962,
          "p99_ms": 0.699504049999962,
          "max_ms": 7.96663599999988,
          "mean_ms": 0.41158947613169244,
          "rsd_pct": 3.848800988994072,
          "throughput": {
            "value": 2732,
            "unit": "ops/s"
          }
        },
        {
          "name": "formatting.markdown.long",
          "iterations": 4,
          "samples": 4,
          "min_ms": 16.71867599999996,
          "p50_ms": 18.95621200000005,
          "p95_ms": 39.042077520000234,
          "p99_ms": 39.042077520000234,
          "max_ms": 44.2860340000002,
          "mean_ms": 22.847057259999996,
          "rsd_pct": 7.7360286673347725,
          "throughput": {
            "value": 47,
            "unit": "ops/s"
          }
        },
        {
          "name": "formatting.markdown.with_xss",
          "iterations": 4,
          "samples": 4,
          "min_ms": 0.23599800000010873,
          "p50_ms": 0.29765499999939493,
          "p95_ms": 0.5966549799999202,
          "p99_ms": 0.5966549799999202,
          "max_ms": 8.250217999999677,
          "mean_ms": 0.3417474687393189,
          "rsd_pct": 3.7928610354038197,
          "throughput": {
            "value": 3221,
            "unit": "ops/s"
          }
        },
        {
          "name": "formatting.regex_hooks.10",
          "iterations": 4,
          "samples": 4,
          "min_ms": 0.21856100000059087,
          "p50_ms": 0.2711234999997032,
          "p95_ms": 0.4685473500000633,
          "p99_ms": 0.4685473500000633,
          "max_ms": 18.809056000000055,
          "mean_ms": 0.3081309140480567,
          "rsd_pct": 5.529399240273528,
          "throughput": {
            "value": 3616,
            "unit": "ops/s"
          }
        },
        {
          "name": "formatting.full_pipeline.100msg",
          "iterations": 4,
          "samples": 4,
          "min_ms": 25.047927000000527,
          "p50_ms": 30.29122600000028,
          "p95_ms": 59.67415365999993,
          "p99_ms": 59.67415365999993,
          "max_ms": 67.97316899999987,
          "mean_ms": 32.22324992000008,
          "rsd_pct": 6.988269513112089,
          "throughput": {
            "value": 32,
            "unit": "ops/s"
          }
        }
      ]
    }
  }
}